confeasy/azure_appc.py
confeasy_azure_appc-1.0.0.dist-info/LICENSE
confeasy_azure_appc-1.0.0.dist-info/METADATA
confeasy_azure_appc-1.0.0.dist-info/WHEEL
confeasy_azure_appc-1.0.0.dist-info/RECORD
