Metadata-Version: 2.1
Name: confeasy-azure-appc
Version: 1.0.0
Summary: Azure AppConfiguration extension for confeasy.
Home-page: https://github.com/jdvor/confeasy-azure-appc
License: MIT
Keywords: configuration,azure,AppConfiguration
Author: jan Dvorak
Author-email: jandvorak.public@gmail.com
Requires-Python: >=3.12,<4.0
Classifier: License :: OSI Approved :: MIT License
Classifier: Programming Language :: Python :: 3
Classifier: Programming Language :: Python :: 3.12
Classifier: Programming Language :: Python :: 3.13
Requires-Dist: azure-appconfiguration (>=1.7.1,<2.0.0)
Requires-Dist: azure-identity (>=1.19.0,<2.0.0)
Requires-Dist: azure-keyvault-secrets (>=4.9.0,<5.0.0)
Project-URL: Bug Tracker, https://github.com/jdvor/confeasy-azure-appc/issues
Project-URL: Repository, https://github.com/jdvor/confeasy-azure-appc
